llm_bench/__init__.py
llm_bench/cache.py
llm_bench/cli.py
llm_bench/compare.py
llm_bench/config.py
llm_bench/data.py
llm_bench/export.py
llm_bench/git_utils.py
llm_bench/init.py
llm_bench/llm.py
llm_bench/metrics.py
llm_bench/models.py
llm_bench/output.py
llm_bench/py.typed
llm_bench/runner.py
llm_bench/validation.py
llm_bench_cli-0.2.0.dist-info/METADATA
llm_bench_cli-0.2.0.dist-info/WHEEL
llm_bench_cli-0.2.0.dist-info/entry_points.txt
llm_bench_cli-0.2.0.dist-info/licenses/LICENSE
llm_bench_cli-0.2.0.dist-info/RECORD
