Metadata-Version: 2.4
Name: llm-bench-cli
Version: 0.2.0
Summary: A developer-centric CLI tool to systematically evaluate and compare Large Language Models (LLMs)
Project-URL: Homepage, https://github.com/abdulbb/llm-bench-cli
Project-URL: Repository, https://github.com/abdulbb/llm-bench-cli.git
Project-URL: Issues, https://github.com/abdulbb/llm-bench-cli/issues
Project-URL: Documentation, https://github.com/abdulbb/llm-bench-cli#readme
Project-URL: Changelog, https://github.com/abdulbb/llm-bench-cli/releases
Author: Abdul Basit Banbhan
License: MIT License
License-File: LICENSE
Keywords: ai,anthropic,benchmark,claude,cli,evaluation,gemini,gpt,llm,openai,testing
Classifier: Development Status :: 4 - Beta
Classifier: Environment :: Console
Classifier: Intended Audience :: Developers
Classifier: Intended Audience :: Science/Research
Classifier: License :: OSI Approved :: MIT License
Classifier: Operating System :: OS Independent
Classifier: Programming Language :: Python :: 3
Classifier: Programming Language :: Python :: 3.10
Classifier: Programming Language :: Python :: 3.11
Classifier: Programming Language :: Python :: 3.12
Classifier: Programming Language :: Python :: 3.13
Classifier: Topic :: Scientific/Engineering :: Artificial Intelligence
Classifier: Topic :: Software Development :: Quality Assurance
Classifier: Topic :: Software Development :: Testing
Classifier: Typing :: Typed
Requires-Python: >=3.10
Requires-Dist: deepdiff>=6.0.0
Requires-Dist: diskcache>=5.6.0
Requires-Dist: litellm>=1.0.0
Requires-Dist: pydantic>=2.0.0
Requires-Dist: python-dotenv>=1.0.0
Requires-Dist: pyyaml>=6.0.0
Requires-Dist: rich>=13.0.0
Requires-Dist: typer>=0.9.0
Provides-Extra: dev
Requires-Dist: mypy>=1.0.0; extra == 'dev'
Requires-Dist: pytest-asyncio>=0.21.0; extra == 'dev'
Requires-Dist: pytest-cov>=4.0.0; extra == 'dev'
Requires-Dist: pytest>=7.0.0; extra == 'dev'
Requires-Dist: ruff>=0.1.0; extra == 'dev'
Requires-Dist: types-pyyaml>=6.0.0; extra == 'dev'
